authos/__init__.py
authos/authos.py
authos-0.0.6.dist-info/LICENSE
authos-0.0.6.dist-info/METADATA
authos-0.0.6.dist-info/WHEEL
authos-0.0.6.dist-info/top_level.txt
authos-0.0.6.dist-info/RECORD
