Metadata-Version: 2.1
Name: authos
Version: 0.0.6
Summary: A package to create membership system.
Author: Sleep
Author-email: ok33355555@gmail.com
Classifier: Programming Language :: Python :: 3
Classifier: License :: OSI Approved :: MIT License
Classifier: Operating System :: OS Independent
Requires-Python: >=3.6
License-File: LICENSE
